{"id":"761436f7-5553-4e08-bcd3-6c7c2eec9fde","timestamp":1749903336348,"matcher":{"static":{"/__nuxt_content/index/sql_dump.txt":{"prerender":true},"/__nuxt_content/projects/sql_dump.txt":{"prerender":true},"/__nuxt_content/blog/sql_dump.txt":{"prerender":true},"/__nuxt_content/pages/sql_dump.txt":{"prerender":true},"/__nuxt_content/speaking/sql_dump.txt":{"prerender":true},"/__nuxt_content/about/sql_dump.txt":{"prerender":true}},"wildcard":{},"dynamic":{}},"prerendered":["/","/speaking","/projects","/about"]}